Workbook

Sheet Dashboard
A1: PORTFÓLIO DE INVESTIMENTOS
A2: Visão executiva de patrimônio, alocação, rentabilidade e proventos
B4: PATRIMÔNIO ATUAL | D4: TOTAL INVESTIDO | F4: LUCRO COTAÇÃO | H4: RENTABILIDADE %
B5: =Consolidado!G13 | D5: =Consolidado!D13 | F5: =Consolidado!H13 | H5: =Consolidado!I13
B7: TOTAL PROVENTOS | D7: RETORNO TOTAL | F7: YIELD ON COST | H7: PREÇO DE TETO ALERTA
B8: =SUM(Proventos!G:G) | D8: =Consolidado!K13 | F8: =Consolidado!L13 | H8: =COUNTIF(Consolidado!M3:M10, "Abaixo do Teto")
A11: ALOCAÇÃO POR CLASSE DE ATIVOS
A12: Categoria | B12: Valor Atual (R$) | C12: % Alocação
A13: Ações | B13: =SUMIF(Consolidado!B$3:B$10, A13, Consolidado!G$3:G$10) | C13: =B13/$B$5
A14: FIIs | B14: =SUMIF(Consolidado!B$3:B$10, A14, Consolidado!G$3:G$10) | C14: =B14/$B$5
A15: Renda Fixa | B15: =SUMIF(Consolidado!B$3:B$10, A15, Consolidado!G$3:G$10) | C15: =B15/$B$5
A16: Cripto | B16: =SUMIF(Consolidado!B$3:B$10, A16, Consolidado!G$3:G$10) | C16: =B16/$B$5
A18: TOP ATIVOS POR VALOR DE MERCADO
A19: Ativo | B19: Categoria | C19: Valor Atual (R$) | D19: % do Total
A20: PETR4 | B20: =VLOOKUP(A20, Consolidado!A$3:B$10, 2, FALSE) | C20: =VLOOKUP(A20, Consolidado!A$3:G$10, 7, FALSE) | D20: =C20/$B$5
A21: VALE3 | B21: =VLOOKUP(A21, Consolidado!A$3:B$10, 2, FALSE) | C21: =VLOOKUP(A21, Consolidado!A$3:G$10, 7, FALSE) | D21: =C21/$B$5
A22: MXRF11 | B22: =VLOOKUP(A22, Consolidado!A$3:B$10, 2, FALSE) | C22: =VLOOKUP(A22, Consolidado!A$3:G$10, 7, FALSE) | D22: =C22/$B$5
A23: HGLG11 | B23: =VLOOKUP(A23, Consolidado!A$3:B$10, 2, FALSE) | C23: =VLOOKUP(A23, Consolidado!A$3:G$10, 7, FALSE) | D23: =C23/$B$5
A24: Tesouro Selic | B24: =VLOOKUP(A24, Consolidado!A$3:B$10, 2, FALSE) | C24: =VLOOKUP(A24, Consolidado!A$3:G$10, 7, FALSE) | D24: =C24/$B$5

Sheet Consolidado
A1: POSIÇÃO CONSOLIDADA E ANÁLISE DE TETO
A2: Ativo | B2: Categoria | C2: Qtd. Total | D2: Total Investido (R$) | E2: Preço Médio (R$) | F2: Preço Atual (R$) | G2: Valor Atual (R$) | H2: Lucro/Prejuízo (R$) | I2: Rentab. Cotação (%) | J2: Proventos (R$) | K2: Retorno Total (R$) | L2: Yield on Cost (%) | M2: Status Preço Teto
A3: PETR4 | B3: Ações | C3: =SUMIFS(Movimentações!E:E, Movimentações!C:C, A3, Movimentações!B:B, "Compra") - SUMIFS(Movimentações!E:E, Movimentações!C:C, A3, Movimentações!B:B, "Venda") | D3: =SUMIFS(Movimentações!H:H, Movimentações!C:C, A3, Movimentações!B:B, "Compra") - SUMIFS(Movimentações!H:H, Movimentações!C:C, A3, Movimentações!B:B, "Venda") | E3: =IF(C3>0, D3/C3, 0) | F3: 32.5 | G3: =C3*F3 | H3: =G3-D3 | I3: =IF(D3>0, H3/D3, 0) | J3: =SUMIF(Proventos!D:D, A3, Proventos!G:G) | K3: =H3+J3 | L3: =IF(D3>0, J3/D3, 0) | M3: =IF(F3<=35.0, "Abaixo do Teto", "Acima do Teto")
A4: VALE3 | B4: Ações | C4: =SUMIFS(Movimentações!E:E, Movimentações!C:C, A4, Movimentações!B:B, "Compra") - SUMIFS(Movimentações!E:E, Movimentações!C:C, A4, Movimentações!B:B, "Venda") | D4: =SUMIFS(Movimentações!H:H, Movimentações!C:C, A4, Movimentações!B:B, "Compra") - SUMIFS(Movimentações!H:H, Movimentações!C:C, A4, Movimentações!B:B, "Venda") | E4: =IF(C4>0, D4/C4, 0) | F4: 68 | G4: =C4*F4 | H4: =G4-D4 | I4: =IF(D4>0, H4/D4, 0) | J4: =SUMIF(Proventos!D:D, A4, Proventos!G:G) | K4: =H4+J4 | L4: =IF(D4>0, J4/D4, 0) | M4: =IF(F4<=65.0, "Abaixo do Teto", "Acima do Teto")
A5: MXRF11 | B5: FIIs | C5: =SUMIFS(Movimentações!E:E, Movimentações!C:C, A5, Movimentações!B:B, "Compra") - SUMIFS(Movimentações!E:E, Movimentações!C:C, A5, Movimentações!B:B, "Venda") | D5: =SUMIFS(Movimentações!H:H, Movimentações!C:C, A5, Movimentações!B:B, "Compra") - SUMIFS(Movimentações!H:H, Movimentações!C:C, A5, Movimentações!B:B, "Venda") | E5: =IF(C5>0, D5/C5, 0) | F5: 10.15 | G5: =C5*F5 | H5: =G5-D5 | I5: =IF(D5>0, H5/D5, 0) | J5: =SUMIF(Proventos!D:D, A5, Proventos!G:G) | K5: =H5+J5 | L5: =IF(D5>0, J5/D5, 0) | M5: =IF(F5<=10.5, "Abaixo do Teto", "Acima do Teto")
A6: HGLG11 | B6: FIIs | C6: =SUMIFS(Movimentações!E:E, Movimentações!C:C, A6, Movimentações!B:B, "Compra") - SUMIFS(Movimentações!E:E, Movimentações!C:C, A6, Movimentações!B:B, "Venda") | D6: =SUMIFS(Movimentações!H:H, Movimentações!C:C, A6, Movimentações!B:B, "Compra") - SUMIFS(Movimentações!H:H, Movimentações!C:C, A6, Movimentações!B:B, "Venda") | E6: =IF(C6>0, D6/C6, 0) | F6: 162 | G6: =C6*F6 | H6: =G6-D6 | I6: =IF(D6>0, H6/D6, 0) | J6: =SUMIF(Proventos!D:D, A6, Proventos!G:G) | K6: =H6+J6 | L6: =IF(D6>0, J6/D6, 0) | M6: =IF(F6<=160.0, "Abaixo do Teto", "Acima do Teto")
A7: Tesouro Selic | B7: Renda Fixa | C7: =SUMIFS(Movimentações!E:E, Movimentações!C:C, A7, Movimentações!B:B, "Compra") - SUMIFS(Movimentações!E:E, Movimentações!C:C, A7, Movimentações!B:B, "Venda") | D7: =SUMIFS(Movimentações!H:H, Movimentações!C:C, A7, Movimentações!B:B, "Compra") - SUMIFS(Movimentações!H:H, Movimentações!C:C, A7, Movimentações!B:B, "Venda") | E7: =IF(C7>0, D7/C7, 0) | F7: 10500 | G7: =C7*F7 | H7: =G7-D7 | I7: =IF(D7>0, H7/D7, 0) | J7: =SUMIF(Proventos!D:D, A7, Proventos!G:G) | K7: =H7+J7 | L7: =IF(D7>0, J7/D7, 0) | M7: =IF(F7<=11000.0, "Abaixo do Teto", "Acima do Teto")
A8: CDB Itaú 110% | B8: Renda Fixa | C8: =SUMIFS(Movimentações!E:E, Movimentações!C:C, A8, Movimentações!B:B, "Compra") - SUMIFS(Movimentações!E:E, Movimentações!C:C, A8, Movimentações!B:B, "Venda") | D8: =SUMIFS(Movimentações!H:H, Movimentações!C:C, A8, Movimentações!B:B, "Compra") - SUMIFS(Movimentações!H:H, Movimentações!C:C, A8, Movimentações!B:B, "Venda") | E8: =IF(C8>0, D8/C8, 0) | F8: 5000 | G8: =C8*F8 | H8: =G8-D8 | I8: =IF(D8>0, H8/D8, 0) | J8: =SUMIF(Proventos!D:D, A8, Proventos!G:G) | K8: =H8+J8 | L8: =IF(D8>0, J8/D8, 0) | M8: =IF(F8<=5200.0, "Abaixo do Teto", "Acima do Teto")
A9: BTC | B9: Cripto | C9: =SUMIFS(Movimentações!E:E, Movimentações!C:C, A9, Movimentações!B:B, "Compra") - SUMIFS(Movimentações!E:E, Movimentações!C:C, A9, Movimentações!B:B, "Venda") | D9: =SUMIFS(Movimentações!H:H, Movimentações!C:C, A9, Movimentações!B:B, "Compra") - SUMIFS(Movimentações!H:H, Movimentações!C:C, A9, Movimentações!B:B, "Venda") | E9: =IF(C9>0, D9/C9, 0) | F9: 320000 | G9: =C9*F9 | H9: =G9-D9 | I9: =IF(D9>0, H9/D9, 0) | J9: =SUMIF(Proventos!D:D, A9, Proventos!G:G) | K9: =H9+J9 | L9: =IF(D9>0, J9/D9, 0) | M9: =IF(F9<=350000.0, "Abaixo do Teto", "Acima do Teto")
A10: ETH | B10: Cripto | C10: =SUMIFS(Movimentações!E:E, Movimentações!C:C, A10, Movimentações!B:B, "Compra") - SUMIFS(Movimentações!E:E, Movimentações!C:C, A10, Movimentações!B:B, "Venda") | D10: =SUMIFS(Movimentações!H:H, Movimentações!C:C, A10, Movimentações!B:B, "Compra") - SUMIFS(Movimentações!H:H, Movimentações!C:C, A10, Movimentações!B:B, "Venda") | E10: =IF(C10>0, D10/C10, 0) | F10: 18000 | G10: =C10*F10 | H10: =G10-D10 | I10: =IF(D10>0, H10/D10, 0) | J10: =SUMIF(Proventos!D:D, A10, Proventos!G:G) | K10: =H10+J10 | L10: =IF(D10>0, J10/D10, 0) | M10: =IF(F10<=17500.0, "Abaixo do Teto", "Acima do Teto")
A13: TOTAL CARTEIRA | D13: =SUM(D3:D10) | G13: =SUM(G3:G10) | H13: =SUM(H3:H10) | I13: =IF(D13>0, H13/D13, 0) | J13: =SUM(J3:J10) | K13: =SUM(K3:K10) | L13: =IF(D13>0, J13/D13, 0)

Sheet Proventos
A1: HISTÓRICO DE PROVENTOS RECEBIDOS
A2: Data Com | B2: Data Pagamento | C2: Tipo Provento | D2: Ativo | E2: Qtd. Custódia | F2: Valor/Cota (R$) | G2: Total Recebido (R$)
A3: 2026-01-15 | B3: 2026-01-30 | C3: Dividendo | D3: PETR4 | E3: 100 | F3: 1.25 | G3: =E3*F3
A4: 2026-01-31 | B4: 2026-02-15 | C4: Rendimento | D4: MXRF11 | E4: 200 | F4: 0.1 | G4: =E4*F4
A5: 2026-01-31 | B5: 2026-02-15 | C5: Rendimento | D5: HGLG11 | E5: 15 | F5: 1.1 | G5: =E5*F5
A6: 2026-02-10 | B6: 2026-02-28 | C6: JCP | D6: VALE3 | E6: 50 | F6: 2.1 | G6: =E6*F6
A7: 2026-02-28 | B7: 2026-03-15 | C7: Rendimento | D7: MXRF11 | E7: 200 | F7: 0.11 | G7: =E7*F7
A8: 2026-02-28 | B8: 2026-03-15 | C8: Rendimento | D8: HGLG11 | E8: 15 | F8: 1.1 | G8: =E8*F8
A9: TOTAL PROVENTOS | G9: =SUM(G3:G8)

Sheet Movimentações
A1: REGISTRO DE OPERAÇÕES DE COMPRA E VENDA
A2: Data | B2: Tipo Operação | C2: Ativo | D2: Categoria | E2: Quantidade | F2: Preço Unitário (R$) | G2: Taxas/Corretagem (R$) | H2: Total Operação (R$)
A3: 2026-01-10 | B3: Compra | C3: PETR4 | D3: Ações | E3: 100 | F3: 30 | G3: 2.5 | H3: =(E3*F3)+G3
A4: 2026-01-15 | B4: Compra | C4: VALE3 | D4: Ações | E4: 50 | F4: 62 | G4: 3 | H4: =(E4*F4)+G4
A5: 2026-02-01 | B5: Compra | C5: MXRF11 | D5: FIIs | E5: 200 | F5: 10 | G5: 0 | H5: =(E5*F5)+G5
A6: 2026-02-05 | B6: Compra | C6: HGLG11 | D6: FIIs | E6: 15 | F6: 158 | G6: 0 | H6: =(E6*F6)+G6
A7: 2026-02-10 | B7: Compra | C7: Tesouro Selic | D7: Renda Fixa | E7: 1 | F7: 10000 | G7: 0 | H7: =(E7*F7)+G7
A8: 2026-02-15 | B8: Compra | C8: CDB Itaú 110% | D8: Renda Fixa | E8: 1 | F8: 5000 | G8: 0 | H8: =(E8*F8)+G8
A9: 2026-02-20 | B9: Compra | C9: BTC | D9: Cripto | E9: 0.05 | F9: 300000 | G9: 15 | H9: =(E9*F9)+G9
A10: 2026-02-25 | B10: Compra | C10: ETH | D10: Cripto | E10: 0.5 | F10: 17000 | G10: 5 | H10: =(E10*F10)+G10
A11: TOTAL OPERADO | H11: =SUM(H3:H10)

Sheet Rebalanceamento
A1: REBALANCEAMENTO DE CARTEIRA (METAS DE ALOCAÇÃO)
A2: Categoria | B2: Valor Atual (R$) | C2: % Atual | D2: % Meta | E2: Diferença (%) | F2: Ajuste Sugerido (R$) | G2: Ação Recomendada
A3: Ações | B3: =SUMIF(Consolidado!B$3:B$10, A3, Consolidado!G$3:G$10) | C3: =B3/Dashboard!$B$5 | D3: 0.3 | E3: =C3-D3 | F3: =(D3*Dashboard!$B$5)-B3 | G3: =IF(F3>0, "Aportar", IF(F3<0, "Ajustar/Aguardar", "Em Meta"))
A4: FIIs | B4: =SUMIF(Consolidado!B$3:B$10, A4, Consolidado!G$3:G$10) | C4: =B4/Dashboard!$B$5 | D4: 0.3 | E4: =C4-D4 | F4: =(D4*Dashboard!$B$5)-B4 | G4: =IF(F4>0, "Aportar", IF(F4<0, "Ajustar/Aguardar", "Em Meta"))
A5: Renda Fixa | B5: =SUMIF(Consolidado!B$3:B$10, A5, Consolidado!G$3:G$10) | C5: =B5/Dashboard!$B$5 | D5: 0.3 | E5: =C5-D5 | F5: =(D5*Dashboard!$B$5)-B5 | G5: =IF(F5>0, "Aportar", IF(F5<0, "Ajustar/Aguardar", "Em Meta"))
A6: Cripto | B6: =SUMIF(Consolidado!B$3:B$10, A6, Consolidado!G$3:G$10) | C6: =B6/Dashboard!$B$5 | D6: 0.1 | E6: =C6-D6 | F6: =(D6*Dashboard!$B$5)-B6 | G6: =IF(F6>0, "Aportar", IF(F6<0, "Ajustar/Aguardar", "Em Meta"))
A7: TOTAL | B7: =SUM(B3:B6) | C7: =SUM(C3:C6) | D7: =SUM(D3:D6)
